cable_extension/__init__.py
cable_extension/forms.py
cable_extension/models.py
cable_extension/navigation.py
cable_extension/template_extensions.py
cable_extension/urls.py
cable_extension/views.py
cable_extension/migrations/0001_initial.py
cable_extension/migrations/__init__.py
cable_extension/templates/cable_extension/cable_create.html
cable_extension/templates/cable_extension/cable_extension_edit.html
cable_extension/templates/cable_extension/cable_extension_panel.html
cable_extension-1.0.1.dist-info/licenses/LICENSE
cable_extension-1.0.1.dist-info/METADATA
cable_extension-1.0.1.dist-info/WHEEL
cable_extension-1.0.1.dist-info/top_level.txt
cable_extension-1.0.1.dist-info/RECORD
