Metadata-Version: 2.4
Name: cable_extension
Version: 1.0.1
Summary: Plugin for extending cable data and integrating with inventory.
Author-email: Viktor Kubec <Viktor.Kubec@gmail.com>
License-Expression: MIT
Classifier: Programming Language :: Python :: 3
Classifier: Operating System :: OS Independent
Requires-Python: >=3.8
License-File: LICENSE
Dynamic: license-file
